invoice_generator/__init__.py
invoice_generator/generator.py
invoice_generator_by_podpivas-0.1.0.dist-info/METADATA
invoice_generator_by_podpivas-0.1.0.dist-info/WHEEL
invoice_generator_by_podpivas-0.1.0.dist-info/top_level.txt
invoice_generator_by_podpivas-0.1.0.dist-info/RECORD
